mint/__init__.py
mindlab_toolkit-0.0.1.dist-info/METADATA
mindlab_toolkit-0.0.1.dist-info/WHEEL
mindlab_toolkit-0.0.1.dist-info/licenses/LICENSE
mindlab_toolkit-0.0.1.dist-info/RECORD
