Metadata-Version: 2.4
Name: mindlab-toolkit
Version: 0.0.1
Summary: Mind Lab Toolkit (MinT) - the Open Infrastructure for Experiential Intelligence
Project-URL: Homepage, https://macaron.im/mindlab
Author: Mind Lab
License-Expression: MIT
License-File: LICENSE
Keywords: lora,mindlab,mint,ml,reinforcement-learning,tinker,training
Classifier: Development Status :: 2 - Pre-Alpha
Classifier: Intended Audience :: Developers
Classifier: License :: OSI Approved :: MIT License
Classifier: Programming Language :: Python :: 3
Classifier: Programming Language :: Python :: 3.9
Classifier: Programming Language :: Python :: 3.10
Classifier: Programming Language :: Python :: 3.11
Classifier: Programming Language :: Python :: 3.12
Requires-Python: >=3.9
Requires-Dist: tinker
